octoparse_api_client/__init__.py
octoparse_api_client-0.1.1.dist-info/AUTHORS.rst
octoparse_api_client-0.1.1.dist-info/METADATA
octoparse_api_client-0.1.1.dist-info/WHEEL
octoparse_api_client-0.1.1.dist-info/top_level.txt
octoparse_api_client-0.1.1.dist-info/RECORD
