Metadata-Version: 2.1
Name: octoparse-api-client
Version: 0.1.1
Summary: client for OctoParse
Home-page: https://gitlab.com/rwconequip/octoparse-api-client
Author: R W
Author-email: rob.w@conequip.com
License: UNKNOWN
Keywords: octoparse_api_client
Platform: UNKNOWN
Classifier: Development Status :: 2 - Pre-Alpha
Classifier: Intended Audience :: Developers
Classifier: Natural Language :: English
Classifier: Programming Language :: Python :: 3
Classifier: Programming Language :: Python :: 3.6
Classifier: Programming Language :: Python :: 3.7
Requires-Python: >=3.6
License-File: AUTHORS.rst
Requires-Dist: requests
